{
  "chapter": "3",
  "verse": "3.43",
  "sanskrit_verse": "एवं बुद्धेः परं बुद्ध्वा संस्तभ्यात्मानमात्मना। जहि शत्रुं महाबाहो कामरूपं दुरासदम्॥",
  "sanskrit": "आत्मनः कामरूपं शत्रुं इति चिन्त्य परबुद्ध्या आत्मनियमनं कर्तव्यम्।  \nएवं आत्मनियमनात् शान्ति, सुखं च प्राप्तुं शक्यते।  \nपरिणामे मोक्षमार्गे अग्रेण पन्था प्रवर्तते।",
  "punjabi": "ਜਦੋਂ ਇੱਛਾ ਤੇ ਅਹੰਕਾਰ ਦੀ ਲੜਾਈ ਮਨ ਨੂੰ ਝਕਮੋੜਦੀ ਹੈ, ਆਪਣੀ ਅਸਲੀ ਬੁੱਧੀ ਨੂੰ ਪਛਾਣ ਕੇ ਆਪ ਨੂੰ ਅੰਦਰੋਂ ਮਜ਼ਬੂਤ ਕਰ।  \nਇਸ ਨਾਲ ਮਨ ਦੀ ਸ਼ਾਂਤੀ, ਸੱਚੀ ਖੁਸ਼ੀ ਅਤੇ ਅੰਦਰੂਨੀ ਸੁਖ ਮਿਲਦਾ ਹੈ।  \nਫਿਰ ਜੀਵਨ ਵਿੱਚ ਅਸਲੀ ਆਜ਼ਾਦੀ, ਉੱਚੀ ਸਚੇਤਨਾ ਅਤੇ ਅਨੰਤ ਆਤਮ-ਸਮਰਪਣ ਦਾ ਅਨੁਭਵ ਹੁੰਦਾ ਹੈ।",
  "hindi": "जब इच्छा हमें बंधन बनाकर सताती है, तो आत्म‑नियंत्रण से उसे पराजित करें।  \nइससे मन शुद्ध हो जाता है और सच्ची शांति प्राप्त होती है।  \nजीवन में स्पष्ट दिशा, आत्म‑विश्वास और स्थायी सुख का विकास होता है।",
  "english": "When desire clouds the mind, recognize the higher wisdom within and stand firm in your true self, then decisively cut through that lust‑driven impulse.  \nDoing so steadies the heart, freeing you from inner turmoil and fostering lasting inner peace.  \nIt also cultivates clear purpose, allowing you to act with confidence and harmony in every aspect of life.",
  "gujarati": "અસંતોષ અને ઇચ્છાઓથી પીડાતા મનને, ઊંચી બુદ્ધિથી આત્મનિયંત્રણ કરીને નાશ કરવું.  \nએથી મનમાં શાંતિ અને સ્પષ્ટતા મળે છે.  \nજીવનમાં સાચી સ્વતંત્રતા અને આનંદ પ્રગટે છે.",
  "tamil": "மனத்தின் ஆசை என்ற எதிரியை, உயர்ந்த ஞானம் கொண்டு சுய கட்டுப்பாட்டால் வெல்ல வேண்டும்.  \nஇதைச் செய்யும் போது மனம் சாந்தியடைந்து, வாழ்க்கை தெளிவாகும்.  \nஅதனால் நம் செயல் சுதந்திரமாகும், ஆன்மீக வளர்ச்சி உறுதியாகும்.",
  "telugu": "మనలోని కోరికల శత్రువును, ఉన్నత బుద్ధి ద్వారా స్వయంగా నియంత్రించి నాశనం చేయాలి.  \nఅంతర్గత శాంతి, మానసిక స్థిరత్వం పొందుతాం.  \nనిజమైన స్వాతంత్ర్యం, జీవనంలో సుఖ‑సమృద్ధి వస్తుంది.",
  "kannada": "ನಮ್ಮ ಮನಸ್ಸು ಕಮೆ ಮತ್ತು ಅಸಂತೃಪ್ತಿಯೊಂದಿಗೆ ಹೋರಾಡುವಾಗ, ಸ್ವಯಂ ಜ್ಞಾನವನ್ನು ಅರಿತು, ಆತ್ಮದಲ್ಲಿ ದೃಢವಾಗಿ ನಿಂತು ಕಮೆಯನ್ನು ನಾಶ ಮಾಡಬೇಕು.  \nಇದರಿಂದ ಮನಸ್ಸು ಶಾಂತವಾಗುತ್ತದೆ, ಅಂತರಂಗದ ಶಕ್ತಿ ಹೆಚ್ಚುತ್ತದೆ.  \nಜೀವನದಲ್ಲಿ ಸ್ಪಷ್ಟತೆ, ಧೈರ್ಯ ಮತ್ತು ನಿಜವಾದ ಸಂತೃಪ್ತಿ ದೊರೆಯುತ್ತದೆ."
}