{
  "chapter": "4",
  "verse": "4.30",
  "sanskrit_verse": "अपरे नियताहाराः प्राणान्प्राणेषु जुह्वति। सर्वेऽप्येते यज्ञविदो यज्ञक्षपितकल्मषाः॥",
  "sanskrit": "असत्यभोजनस्य कारणेन मनः क्लेशः, शुद्धयज्ञभोजनं स्वीकुर्वीत।  \nएवम् आत्मा शुद्धः स्यात्, पापक्लेशः लुप्तः।  \nसत्सङ्गे च मोक्षमार्गेण प्रगच्छति।",
  "punjabi": "ਬੇਸੁਧੀ ਖਾਣ-ਪੀਣ ਅਤੇ ਬਾਹਰੀ ਯਜਨਾਵਾਂ 'ਤੇ ਝੁਕਾਅ ਮਨ ਦੀ ਊਰ",
  "hindi": "जब हम बिना विचार के दूसरों के तय किए हुए भोजन को ग्रहण करते हैं, तो अपनी आत्मा को उनके कर्मों में बंधा पाते हैं; इसलिए अपना आहार और कर्म शुद्ध इरादे से चुनें।  \nऐसा करने से मन में शांति आती है, पापों का बोझ हल्का होता है और आत्मा शुद्ध हो जाती है।  \nपरिणामस्वरूप हम यज्ञ की सच्ची भावना को समझते हुए जीवन में सच्ची स्वतंत्रता और आनंद प्राप्त करते हैं।",
  "english": "When we eat food that hasn’t been offered in a proper sacrifice, we sap our own life‑energy; the cure is to accept only food sanctified by a true yajna.  \nDoing this keeps our mind and body vibrant, safeguarding health and inner peace.  \nIt also clears karmic stains, letting us live in harmony with dharma.",
  "gujarati": "ખોરાકની ગલત પસંદગી અને અણગમતા ઇચ્છાઓને છોડીને, નિર્ધારિત આહાર અપનાવી જીવનને યજ્ઞ રૂપે સમર્પિત કરવું।  \nઆ રીતે મન અને શરીર શુદ્ધ થાય છે, અને આત્મા શાંતિ અને સ્વચ્છતા પ્રાપ્ત કરે છે।  \nયજ્ઞની જાણ ધરાવતા વ્યક્તિને પાપોનું નિરાકરણ મળે છે, અને જીવનમાં સત્ય અને મુક્તિનો અનુભવ થાય છે।",
  "tamil": "தன்னலமற்ற உணவு பகிர்வு, மற்றவர்களின் வாழ்க்கையை ஆதரித்து, தம்மை அர்ப்பணிக்கும் செயல்.  \nஇது பாவங்களை அழித்து, ஆன்மாவின் தூய்மையை அதிகரிக்கிறது.  \nஅதனால் மன அமைதி, ஆனந்தம், மற்றும் வாழ்க்கை முழுமை பெறப்படும்.",
  "telugu": "అనుచిత ఆహారపు అలవాట్లు మన శరీర‑ప్రాణాన్ని బలహీనపరచి, అంతర్గత అసంతృప్తి, పాప‑భారం కలిగిస్తాయి; సక్రమమైన ఆహార నియమాన్ని పాటించడం ద్వారా ఈ సమస్యను పరిష్కరించవచ్చు.  \nసరైన ఆహారం తీసుకోవడం ద్వారా శరీరం శుద్ధి, మనసు శాంతి, యజ్ఞ‑సమర్ధత పెరుగుతుంది.  \nఇలా జీవిస్తే పాప‑కల్మషాలు తగ్గి, ఆధ్యాత్మిక వికాసం, సుఖ‑సంపూర్ణ జీవితం లభిస్తుంది.",
  "kannada": "ಅಪವಿತ್ರ ಆಹಾರವನ್ನು ತಿನ್ನುವುದರಿಂದ ಜೀವಶಕ್ತಿ ಹಾನಿಗೊಳಗಾಗುತ್ತದೆ; ಆದ್ದರಿಂದ ಶುದ್ಧ ಯಜ್ಞದೊಂದಿಗೆ ಸಮರ್ಪಿತವಾದ ಆಹಾರವನ್ನು ಮಾತ್ರ ಸೇವಿಸಬೇಕು.  \nಇದರಿಂದ ದೇಹ‑ಮನಸ್ಸು ಶುದ್ಧವಾಗಿದ್ದು, ಆತ್ಮಶಾಂತಿ ಹಾಗೂ ಆರೋಗ್ಯವನ್ನು ಪಡೆಯುತ್ತೇವೆ.  \nಇದು ಜೀವನದ ಉದ್ದೇಶವನ್ನು ಸ್ಪಷ್ಟಗೊಳಿಸಿ, ಆತ್ಮವಿಕಾಸ ಮತ್ತು ಧಾರ್ಮಿಕ ಕರ್ಮಗಳಲ್ಲಿ ಯಶಸ್ಸು ತರಿಸುತ್ತದೆ."
}
