{
  "chapter": "4",
  "verse": "4.32",
  "sanskrit_verse": "एवं बहुविधा यज्ञा वितता ब्रह्मणो मुखे। कर्मजान्विद्धि तान्सर्वानेवं ज्ञात्वा मोक्ष्यसे॥",
  "sanskrit": "मनस्य द्वन्द्वे कर्तव्ये शङ्का यदा, सर्वे यज्ञाः कर्मरूपेण ज्ञातुं प्रयत्नः करोति।  \nएतद् ज्ञानम् आत्मनः शान्तिं लभते।  \nशान्तिं प्राप्त्वा मोक्षस्य द्वारं उद्घाटयति।",
  "punjabi": "ਜਦੋਂ ਕਈ ਤਰ੍ਹਾਂ ਦੇ ਯਾਗ‑ਕਰਮਾਂ ਨਾਲ ਘੁੰਮਦੇ ਹਾਂ, ਉਨ੍ਹਾਂ ਨੂੰ ਬ੍ਰਹਮ ਦੇ ਸਾਹਮਣੇ ਸੱਚੀ ਭਗਤੀ ਵਜੋਂ ਸਮਝ ਕੇ, ਹਰ ਕਰਮ ਨੂੰ ਪੂਰੇ ਮਨ ਨਾਲ ਕਰੀਏ।  \nਇਸ ਤਰ੍ਹਾਂ ਕਰਮਾਂ ਨੂੰ ਯਾਗ ਮੰਨਣ ਨਾਲ ਮਨ ਦੀ ਸ਼ਾਂਤੀ ਅਤੇ ਅੰਦਰੂਨੀ ਸੰਤੁਲਨ ਮਿਲਦਾ ਹੈ।  \nਜਾਣ‑ਪਛਾਣ ਨਾਲ ਇਹ ਕਰਮ ਅੰਤ ਵਿੱਚ ਮੁਕਤੀ ਦੀ ਓਰ ਲੈ ਜਾਂਦੇ ਹਨ।",
  "hindi": "कई प्रकार के यज्ञों से उलझन में हैं? उन्हें केवल कर्म के रूप में समझो और ब्रह्म के सामने उनका ज्ञान प्राप्त करो।  \nऐसा करने से मन शुद्ध होता है और आध्यात्मिक दिशा स्पष्ट होती है।  \nअंत में आत्मा को मोक्ष की प्राप्ति होती है, जिससे सच्ची शांति और स्वतंत्रता मिलती है।",
  "english": "When you feel overwhelmed by countless tasks, recognize each sincere action as a sacrifice offered to the divine.  \nSeeing work as worship quiets the ego and brings lasting inner peace.  \nThat awareness clears the way to true freedom beyond birth and death.",
  "gujarati": "જીવનમાં કર્તવ્ય અને યજ્ઞની ગૂંચવણમાં ફસાઈએ છીએ, તેથી બ્રહ્મના મુખે પ્રસ્તુત વિવિધ યજ્ઞોનું જ્ઞાન મેળવી તેમને કર્મ તરીકે ઓળખો.  \nઆ રીતે કર્તવ્યને સાચી સમજ સાથે નિભાવવાથી મનમાં શાંતિ અને આત્મસંતોષ મળે છે.  \nજાણીને અને સમર્પિત રીતે યજ્ઞોનું પાલન કરવાથી મુક્તિનો માર્ગ ખુલ્લો થાય છે.",
  "tamil": "பல விதமான யஜ்ஞைகள் பலமாகத் தோன்றும் போது, அவற்றை “காரியம்” என்று அறிந்து, சிந்தனையுடன் செய்ய வேண்டும்.  \nஇதனால் மனம் சுத்தமாகி, வாழ்க்கையில் தெளிவும் அமைதியும் கிடைக்கும்.  \nஇறுதியில் சுயமோட்சம், பிறப்பும் மரணமும் மீறிய நித்திய சுதந்திரம் பெறலாம்.",
  "telugu": "బ్రహ్ముని సన్నిధిలో అనేక యజ్ఞాలు కనిపిస్తే, వాటిని కర్మగా గుర్తించి, అంతర్గతంగా అర్థం చేసుకోవాలి.  \nఅలా చేయడం ద్వారా యజ్ఞాల బంధనాలు తొలగి, మన జీవితం స్వచ్ఛతతో నిండి ఉంటుంది.  \nఇది చివరికి పరమmoksha‑కి దారి చూపుతుంది, ఆత్మకు శాంతి, సత్యాన్వేషణను అందిస్తుంది.",
  "kannada": "ವಿವಿಧ ಯಜ್ಞಗಳ ಗೊಂದಲದಿಂದ ತೊಂದರೆಯಾಗುವವರು, ಅವುಗಳನ್ನು ಬ್ರಹ್ಮನ ಕೃತ್ಯಗಳೆಂದು ತಿಳಿದು, ಜ್ಞಾನದಿಂದ ನಡೆಸಬೇಕು.  \nಇದರಿಂದ ಮನಸ್ಸು ಶಾಂತವಾಗುತ್ತದೆ, ಜೀವನದಲ್ಲಿ ಅರ್ಥ ಮತ್ತು ಸಮಾಧಾನ ದೊರೆಯುತ್ತದೆ.  \nಅಂತಿಮವಾಗಿ ಮೋಕ್ಷದ ದಾರಿ ತೆರೆದಿಕೊಳ್ಳಿ, ಸ್ವತಃ ಸ್ವಾತಂತ್ರ್ಯ ಮತ್ತು ಶಾಶ್ವತ ಸಂತೋಷವನ್ನು ಅನುಭವಿಸಬಹುದು."
}