{
  "chapter": "6",
  "verse": "6.32",
  "sanskrit_verse": "आत्मौपम्येन सर्वत्र समं पश्यति योऽर्जुन। सुखं वा यदि वा दुःखं स योगी परमो मतः॥",
  "sanskrit": "सुख‑दुःखयोः बन्धनं त्यजित्वा आत्मौपम्येन सर्वत्र समानं पश्य।  \nमनः शान्तिं लभते, द्वन्द्वेभ्यः विमुक्तिं प्राप्नोति।  \nपरमो योगी भवति, आत्मज्ञानस्य प्रकाशः स्यात्।",
  "punjabi": "ਜਦੋਂ ਅਸੀਂ ਖੁਸ਼ੀ‑ਦੁੱਖ ਵਿੱਚ ਫਸ ਜਾਂਦੇ ਹਾਂ, ਆਪਣੇ ਅਸਲੀ ਸਵਰੂਪ ਨੂੰ ਹਰ ਥਾਂ ਇਕਸਾਰ ਦੇਖਣਾ ਹੀ ਹੱਲ ਹੈ।  \nਇਸ ਤਰ੍ਹਾਂ ਅਸੀਂ ਭਾਵਨਾਵਾਂ ਤੋਂ ਉਪਰ ਉਠ ਕੇ ਸ਼ਾਂਤੀ ਅਤੇ ਸਥਿਰਤਾ ਹਾਸਲ ਕਰਦੇ ਹਾਂ।  \nਫਲਸਰੂਪ, ਜੀਵਨ ਦੇ ਹਰ ਪਲ ਵਿੱਚ ਯੋਗੀ ਦੀ ਤਰ੍ਹਾਂ ਸਮਰਪਿਤ ਅਤੇ ਆਜ਼ਾਦ ਰਹਿੰਦੇ ਹਾਂ।",
  "hindi": "सुख‑दुःख में अंतर महसूस कर उलझन में पड़ते हैं, इसलिए सभी परिस्थितियों को समान दृष्टि से देखना चाहिए।  \nऐसे देखने से मन में शांति और स्थिरता स्थापित होती है।  \nयह हमें सच्चे योगी की तरह जीवन में संतुलन और आत्म‑साक्षात्कार की ओर ले जाता है।",
  "english": "When emotions swing between joy and pain, practice seeing the inner self as the same in every circumstance.  \nThis steadiness creates true inner calm that isn’t shaken by external ups or downs.  \nIt also cultivates the clear, balanced mind of a true yogi, leading to lasting freedom.",
  "gujarati": "જીવનમાં આનંદ‑દુઃખ વચ્ચે ફસાઈ જવું સામાન્ય છે, પરંતુ આત્માને સર્વત્ર સમાન માનીને બધાને સમાન રીતે જોવું જોઈએ।  \nએ રીતે મનમાં શાંતિ અને સમતોલતા ઉભી થાય છે, જે યોગીની સાચી સ્થિતિ છે।  \nઅંતે સત્ય સ્વરૂપની ઓળખ અને મુક્તિ પ્રાપ્ત થાય છે, જે જીવનને અર્થપૂર્ણ બનાવે છે।",
  "tamil": "மகிழ்ச்சி‑வலியால் மனம் அசைவு, ஆன்மாவை எல்லா இடங்களிலும் ஒரே மாதிரி காணும் சமநிலை மனப்பாங்கை வளர்த்துக்கொள்.  \nஇதனால் மனம் அமைதியுடன் நிலைத்து, எந்த சூழலிலும் உள்நிலையைக் காக்கும்.  \nஇறுதியில் சுய‑அறிவு வளர்ந்து, உண்மையான யோகியாக உயர்வை அடைவாய்.",
  "telugu": "సంతోష‑వేదనల మధ్య తేడా చూసి బాధపడే మనసుకు, స్వయాన్ని ప్రతి చోట సమానంగా చూడటం ద్వారా యోగి మారవచ్చు.  \nఅందువల్ల జీవితంలోని ఏ పరిస్థితిలోనైనా మనసు శాంతి, స్థిరత్వాన్ని పొందుతుంది.  \nఇది అంతర్గత స్వేచ్ఛను, సత్య‑జ్ఞానాన్ని పెంచి, పరమ యోగిగా ఎదగడానికి మార్గం చూపుతుంది.",
  "kannada": "ಸಂತೋಷವೂ ದುಃಖವೂ ಬಂದಾಗ, ಆತ್ಮವನ್ನು ಎಲ್ಲೆಡೆ ಒಂದೇ ರೀತಿಯಲ್ಲಿ ನೋಡುವುದು ಪರಿಹಾರ.  \nಇದರಿಂದ ಮನಸ್ಸು ಸ್ಥಿರವಾಗುತ್ತದೆ, ಭಾವನೆಗಳ ಅಲೆಗಳಿಂದ ಮುಕ್ತವಾಗುತ್ತೇವೆ.  \nಅಂತಿಮವಾಗಿ, ಯೋಗಿ ಆಗಿ ಪರಮ ಶಾಂತಿ ಮತ್ತು ಜ್ಞಾನವನ್ನು ಪಡೆಯುತ್ತೇವೆ."
}