{
  "chapter": "6",
  "verse": "6.43",
  "sanskrit_verse": "तत्र तं बुद्धिसंयोगं लभते पौर्वदेहिकम्। यतते च ततो भूयः संसिद्धौ कुरुनन्दन॥",
  "sanskrit": "मनसि अहंकारस्य बन्धनं वर्तते, बुद्धिसंयोगेण तस्य विमोचनम्।  \nएवं मोक्तः जीवः पूर्वजन्मस्य कष्टं त्यजति, शान्तिं लभते।  \nततः परं सिद्ध्यै निरन्तरं प्रयत्नं कृत्वा, आत्मसाक्षात्कारं प्राप्तो भवति।",
  "punjabi": "ਜਦੋਂ ਮਨ ਦੀ ਉਲਝਣ ਅਤੇ ਪੁਰਾਣੀ ਹਾਲਤ ਨਾਲ ਫਸ ਜਾਂਦੇ ਹਾਂ, ਬੁੱਧੀ ਦੀ ਇਕਤਾ ਹਾਸਲ ਕਰਨੀ ਚਾਹੀਦੀ ਹੈ।  \nਇਸ ਨਾਲ ਅੰਦਰੂਨੀ ਸ਼ਾਂਤੀ ਅਤੇ ਆਤਮ-ਸੁਧਾਰ ਦੀ ਸ਼ੁਰੂਆਤ ਹੁੰਦੀ ਹੈ।  \nਫਿਰ ਜੀਵਨ ਵਿੱਚ ਉੱਚੀ ਸਫਲਤਾ ਅਤੇ ਆਤਮਿਕ ਪ੍ਰਗਤੀ ਮਿਲਦੀ ਹੈ।",
  "hindi": "जब मन शरीर में फँसा हो और बुद्धि भटके, तो ईश्वरीय ध्यान से बुद्धि को पूर्व शरीर के साथ मिलाकर स्थिर किया जा सकता है।  \nइससे आत्म‑ज्ञान की गहराई बढ़ती है और जीवन में शांति मिलती है।  \nफिर निरंतर प्रगति और सिद्धि की ओर बढ़ते हुए सच्ची मुक्ति की राह खुलती है।",
  "english": "When the mind feels scattered and trapped in old habits, turn your intellect toward the subtle inner self to regain the deeper, timeless wisdom within.  \nThis steadies the mind, bringing clear awareness and a sense of inner balance.  \nIt then accelerates lasting spiritual growth, leading to lasting peace and fulfillment.",
  "gujarati": "મનની અશાંતિ અને જ્ઞાનની અછતને દૂર કરવા માટે, ભગવાનમાં મનની એકતા અને બુદ્ધિનું સંયોગ મેળવવું જોઈએ.  \nઆથી આંતરિક શાંતિ અને સ્પષ્ટ વિચારશક્તિ મળે છે, જે જીવનમાં સાચો માર્ગ દર્શાવે છે.  \nસતત આ પ્રયોગથી આત્મસાક્ષાત્કાર અને અંતિમ મુક્તિની પ્રાપ્તિ થાય છે.",
  "tamil": "மனம் சிதறி தன்னைக் கண்டறிய முடியாதவர்களுக்கு, உடலின் உணர்வை கவனித்து புத்தியை ஒருங்கிணைப்பது தீர்வு.  \nஇது உள்ளார்ந்த அமைதியையும் சுய அறிவையும் வளர்த்து, வாழ்க்கை தெளிவாகும்.  \nதொடர்ந்து முயற்சி செய்தால் ஆன்மீக உயர்வும் இறுதி விடுதலையும் பெறலாம்.",
  "telugu": "శరీర‑సంబంధిత గందరగోళం, మనస్సు మబ్బుగా ఉండటాన్ని యోగ‑జ్ఞానంతో పూర్వ‑బుద్ధిని తిరిగి పొందండి.  \nఅంతర్గత స్పష్టత, శాంతి, నిర్ణయ‑శక్తి బలపడుతుంది.  \nనిరంతర సాధనతో ఆత్మ‑సంపూర్ణత, పరమ‑సాధన వైపు వేగంగా ముందుకు సాగుతాం.",
  "kannada": "ಮನಸ್ಸಿನ ಅಸ್ಥಿರತೆ ಮತ್ತು ಹಿಂದಿನ ಜೀವನದ ಜ್ಞಾನವನ್ನು ಅರಿಯದ ಕಷ್ಟಕ್ಕೆ, ಬುದ್ಧಿ‑ಪೂರ್ವದೆಹದ ಸಂಯೋಗವನ್ನು ಸಾಧಿಸಬೇಕು.  \nಇದರಿಂದ ಆತ್ಮದ ಶಾಂತಿ, ಜ್ಞಾನವೃದ್ಧಿ ಮತ್ತು ಜೀವನದ ಗುರಿ ಸ್ಪಷ್ಟವಾಗುತ್ತದೆ.  \nಇನ್ನು ಮುಂದೆ ಹೆಚ್ಚುವರಿ ಸಾಧನೆ ಮತ್ತು ಪರಮ ಪರಮಾರ್ಥದ ದಾರಿ ತೆರೆದಿಕೊಳ್ಳುತ್ತದೆ."
}