{
  "chapter": "6",
  "verse": "6.44",
  "sanskrit_verse": "पूर्वाभ्यासेन तेनैव ह्रियते ह्यवशोऽपि सः। जिज्ञासुरपि योगस्य शब्दब्रह्मातिवर्तते॥",
  "sanskrit": "विचलितमनः किल्याणाय निरन्तरपूर्वाभ्यासः आवश्यकः।  \nएतस्मात् मनः स्थिरं भवति, आत्मनियन्त्रं लभते।  \nजिज्ञासु च योगे शब्दब्रह्मात् परे उन्नतिं प्राप्नोति।",
  "punjabi": "ਮਨ ਦੀ ਉਲਝਣ ਜਾਂ ਅਸਮਰੱਥਾ ਮਹਿਸੂਸ ਕਰਦੇ ਹੋ? ਨਿਯਮਿਤ ਅਭਿਆਸ ਅਤੇ ਜਿਗਿਆਸਾ ਨਾਲ ਯੋਗ ਦੀ ਪਾਲਣਾ ਕਰੋ।  \nਇਸ ਨਾਲ ਮਨ ਸ਼ਾਂਤ ਹੁੰਦਾ ਹੈ, ਅੰਦਰੂਨੀ ਸ਼ਕਤੀ ਨਾਲ ਜੋੜ ਮਜ਼ਬੂਤ ਹੁੰਦਾ ਹੈ।  \nਫਿਰ ਤੁਸੀਂ ਸ਼ਬਦ‑ਬ੍ਰਹਮ ਦੀ ਸੀਮਾ ਤੋਂ ਪਰੇ, ਅਸਲ ਸਚਾਈ ਅਤੇ ਆਤਮ‑ਜਾਗਰੂਕਤਾ ਹਾਸਲ ਕਰਦੇ ਹੋ।",
  "hindi": "जब मन बेचैन और अटकलों से घिरा हो, तो निरंतर पूर्वाभ्यास से उसे स्थिर किया जा सकता है और जिज्ञासा को योग के शब्द‑ब्रह्म से परे ले जाया जा सकता है।  \nऐसा करने से मन की शांति गहरी होती है और आत्म‑साक्षात्कार की दिशा में सहजता से बढ़ते हैं।  \nजिज्ञासा का विकास वास्तविक योग अनुभव में बदल जाता है, जिससे जीवन में स्पष्टता और आनंद मिलता है।",
  "english": "Feeling a scattered or overly controlled mind? Regular, dedicated practice and genuine curiosity draw the mind toward yoga’s deeper reality.  \nIt steadies the mind, letting you move beyond the limited sound‑based perception of the world.  \nYou gain lasting inner clarity and a direct connection with the ultimate Brahman.",
  "gujarati": "મનને શાંત અને નિયંત્રિત રાખવામાં મુશ્કેલી હોય તો નિયમિત પૂર્વઅભ્યાસથી તેને આકર્ષિત અને સ્થિર કરી શકાય છે.  \nઆ પ્રેક્ટિસથી મનની અસ્થિરતા દૂર થાય, આંતરિક શાંતિ અને એકાગ્રતા મળે.  \nજિજ્ઞાસા વધે છે, યોગ દ્વારા શબ્દબ્રહ્મની સીમાઓને પાર કરીને ઊંડો આત્મજ્ઞાન પ્રાપ્ત થાય.",
  "tamil": "மனதை கட்டுப்படுத்த முயற்சிக்கும் போது, தினசரி முன் பயிற்சியால் அதை இயல்பாக யோகத்தின் ஈர்ப்புக்கு உட்படுத்தலாம்.  \nஅதனால், ஆர்வம் கொண்டவரும் ஒலி‑பிரம்மத்தின் எல்லைகளை மீறி ஆன்மீக உயர்வை அடைய முடியும்.  \nஇது வாழ்க்கையில் ஆழமான அமைதி, தெளிவு, மற்றும் சுதந்திரத்தை வழங்கும்.",
  "telugu": "అంతర్గత కలకలం లేదా ఆత్మ‑నియంత్రణలో లోపం ఉంటే, రోజువారీ చిన్న యోగ‑ధ్యానం లేదా సాధనతో మనసు స్థిరంగా మారి, ఆసక్తి పెరుగుతుంది.  \nఇది మనకు స్వీయ‑నియంత్రణ బలం, జీవన‑సంతులనం, మరియు అంతర్గత శాంతి అందిస్తుంది.  \nఅదనంగా, జిజ్ఞాసతో కూడిన మనసు పద‑బ్రహ్మాన్ని మించుకుని, నిజమైన ఆత్మ‑జ్ఞానాన్ని అనుభవిస్తుంది.",
  "kannada": "ನಮ್ಮ ಮನಸ್ಸು ಅಸ್ಥಿರವಾಗಿರುವಾಗ, ನಿಯಮಿತ ಧ್ಯಾನ ಮತ್ತು ಅಭ್ಯಾಸದಿಂದ ಅದನ್ನು ಶಾಂತಗೊಳಿಸಬಹುದು.  \nಇದರಿಂದ ಆತ್ಮದ ಶಾಂತಿ ಮತ್ತು ಆಂತರಿಕ ಶಕ್ತಿ ಹೆಚ್ಚುತ್ತದೆ.  \nಅಂತಿಮವಾಗಿ, ಜ್ಞಾನ ಮತ್ತು ಅನುಭವದ ಮೂಲಕ ಶಬ್ದಬ್ರಹ್ಮದ ಮೀರಿದ ನಿಜವಾದ ಏಕತೆಯನ್ನು ಅನುಭವಿಸಬಹುದು."
}