{
  "chapter": "8",
  "verse": "8.5",
  "sanskrit_verse": "अन्तकाले च मामेव स्मरन्मुक्त्वा कलेवरम्। यः प्रयाति स मद्भावं याति नास्त्यत्र संशयः॥",
  "sanskrit": "मृत्यु निकटे भयः उत्पद्यते, किन्तु केवलम् इदं स्मरन्...भगवन् स्मरणम्।  \nएवं स्मरन् आत्मा शान्तिं लभते, मोक्षमार्गे प्रवर्तते।  \nफलतः अनन्तआनन्दः, सर्वभूतेषु प्रेम च जाग्रते।",
  "punjabi": "ਮੌਤ ਦੇ ਸਮੇਂ ਡਰ ਜਾਂ ਉਲਝਣ ਹੁੰਦੀ ਹੈ, ਪਰ ਰੱਬ ਨੂੰ ਯਾਦ ਕਰਕੇ ਅਤੇ ਸ਼ਰੀਰ ਨੂੰ ਛੱਡ ਕੇ ਇਸ ਨੂੰ ਦੂਰ ਕੀਤਾ ਜਾ ਸਕਦਾ ਹੈ।  \nਇਸ ਨਾਲ ਮਨ ਨੂੰ ਅਮਰ ਸ਼ਾਂਤੀ ਮਿਲਦੀ ਹੈ ਅਤੇ ਰੱਬੀ ਸੱਚਾਈ ਨਾਲ ਇਕ ਹੋ ਜਾਂਦੇ ਹਾਂ।  \nਫਲਸਰੂਪ, ਸਾਰੀ ਦੁਖ‑ਦਰਦ ਤੋਂ ਮੁਕਤੀ ਮਿਲਦੀ ਹੈ ਅਤੇ ਅਨੰਤ ਆਤਮਿਕ ਮਿਲਾਪ ਦਾ ਅਨੁਭਵ ਹੁੰਦਾ ਹੈ।",
  "hindi": "मृत्यु के क्षण में जीवन‑संकल्प की उलझन और भय को दूर करने के लिए केवल परमात्मा को स्मरण करके शरीर को त्यागना चाहिए।  \nऐसा करने से आत्मा शुद्ध हो कर भगवान के स्वरूप में परिवर्तित हो जाती है।  \nइस प्रकार अंतिम क्षण में शांति, मोक्ष और अनन्त आनंद प्राप्त होता है।",
  "english": "When death approaches and fear of losing identity arises, simply fix your mind on the Divine and release attachment to the body.  \nDoing this instantly aligns you with the divine nature, bringing deep, lasting peace.  \nIt assures unquestionable liberation, ending all doubt about what follows.",
  "gujarati": "મૃત્યુની ઘડીમાં ભય અને અશાંતિ હોય છે, તેને દૂર કરવા માત્ર ભગવાનને સ્મરણ કરીને શરીર છોડવું જોઈએ.  \nએ રીતે departing soul ને ભગવાનની સ્વભાવ મળે છે, મુક્તિ અને અવિનાશી શાંતિ પ્રાપ્ત થાય છે.  \nઆ અંતિમ જ્ઞાનથી જીવનમાં સત્યનું નિશ્ચય અને આત્મિક સંતોષનું અનુભવ થાય છે.",
  "tamil": "மரணத்தின் பயமும் அடையாளம் இழப்பின் கவலையும், இறுதி நொடியிலே கடவுளை மட்டும் நினைவு கொண்டு உடலை விடுவித்தால் தீரும்.  \nஅதனால் ஆன்மா கடவுளின் நிலைக்கு உயர்ந்து, நிரந்தர அமைதியும் சுதந்திரமும் பெறும்.  \nஇது வாழ்க்கையின் இறுதி சந்தேகமற்ற நிச்சயமான விடுதலையாகும்.",
  "telugu": "మరణ సమీపంలో కలిగే భయం, కేవలం కృష్ణుని స్మరణతో దూరం చేయవచ్చు.  \nఅలా స్మరించి శరీరాన్ని విడిచిపెడితే, మనసు ఆయన సారూప్యానికి చేరుతుంది.  \nఇది శాశ్వత శాంతి, పునర్జన్మ చక్రం నుండి విముక్తి, నిజమైన ఆనందాన్ని అందిస్తుంది.",
  "kannada": "ಮರಣದ ಕ್ಷಣದಲ್ಲಿ ಆತ್ಮದ ಅಸ್ಥಿರತೆ ಮತ್ತು ಭಯವನ್ನು ಎದುರಿಸಲು, ದೇಹವನ್ನು ತೊರೆಯುವಂತೆ ದೇವರನ್ನೇ ಒಂದೇ ಮನಸ್ಸಿನಿಂದ ನೆನಪಿಸಿಕೊಳ್ಳಿ.  \nಇದರಿಂದ ಆತ್ಮ ಶಾಂತಿ ಮತ್ತು ಪರಮ ಸತ್ಯದ ಅನುಭವವನ್ನು ಪಡೆಯುತ್ತೀರಿ.  \nಅಂತಿಮವಾಗಿ ನೀವು ದೈವಿಕ ಸ್ವರೂಪಕ್ಕೆ ಏಕೀಕೃತವಾಗಿ, ನಿರ್ವಾಣದ ಸ್ಥಿತಿಗೆ ಪ್ರವೇಶಿಸುತ್ತೀರಿ."
}