{
  "chapter": "9",
  "verse": "9.33",
  "sanskrit_verse": "किं पुनर्ब्राह्मणाः पुण्या भक्ता राजर्षयस्तथा। अनित्यमसुखं लोकमिमं प्राप्य भजस्व माम॥",
  "sanskrit": "जगति अनित्यमसुखं दृश्यते, अतः मोहम् त्यजित्वा भगवन् भज।  \nतस्मात् शान्ति मनसि वर्तते, दुःखभयं निवार्यते।  \nअन्ते मोक्षस्य प्राप्तिर्भवति, अनन्तानन्दः अनुभूयते।",
  "punjabi": "ਜਦੋਂ ਅਸੀਂ ਸਮਾਜਿਕ ਦਰਜੇ, ਪਵਿੱਤਰ ਲੋਕਾਂ ਜਾਂ ਰਾਜਾ-ਰਾਜਿਆਂ ਦੀ ਤਲਾਸ਼ ਕਰਦੇ ਹਾਂ, ਪਰ ਇਹ ਸੰਸਾਰ ਅਸਥਾਈ ਤੇ ਦੁੱਖ ਨਾਲ ਭਰਿਆ ਹੈ; ਇਸ ਲਈ ਸਿੱਧਾ ਪ੍ਰਭੂ ਦੀ ਭਗਤੀ ਕਰਨੀ ਚਾਹੀਦੀ ਹੈ।  \nਇਸ ਭਗਤੀ ਨਾਲ ਮਨ ਨੂੰ ਅਸਲ ਸ਼ਾਂਤੀ ਮਿਲਦੀ ਹੈ ਅਤੇ ਦੁਨੀਆ ਦੀ ਝੁਲਸੀਆਂ ਤੋਂ ਮੁਕਤੀ ਮਿਲਦੀ ਹੈ।  \nਅੰਤ ਵਿੱਚ ਆਤਮਿਕ ਮੁਕਤੀ ਅਤੇ ਸੱਚੀ ਖੁਸ਼ੀ ਪ੍ਰਾਪਤ ਹੁੰਦੀ ਹੈ, ਜੋ ਸਦੀਵ ਰਹਿੰਦੀ ਹੈ।",
  "hindi": "इस अस्थिर और दुःखभरे संसार में हम अक्सर ब्राह्मण‑भक्तों की राह खोजते हैं, पर श्लोक कहता है कि सीधे परमात्मा की भक्ति ही सच्चा उपाय है।  \nऐसी भक्ति से मन को शाश्वत शांति और सच्ची संतुष्टि मिलती है।  \nअंततः यह हमें जन्म‑मृत्यु के चक्र से मुक्त कर आत्मा की मुक्ति की ओर ले जाता है।",
  "english": "Chasing status, wealth, or praise only fuels anxiety in a world that’s fleeting and full of suffering; the remedy is to shift your focus to sincere devotion to the Divine.  \nThis steadies the mind, freeing you from the restless pursuit of external validation.  \nIt brings lasting inner peace and a deeper sense of purpose beyond the temporary world.",
  "gujarati": "જીવનની અસ્થિરતા અને દુઃખથી પીડાતા લોકો માટે, બાહ્ય ઉપદેશકો પર નિર્ભરતા છોડીને સીધો ભગવાનની ભક્તિ અપનાવવી જોઈએ.  \nઆ રીતે મનની શાંતિ અને આંતરિક સ્થિરતા પ્રાપ્ત થાય છે.  \nસત્યની જ્ઞાનથી મુક્તિ અને સત્ય આનંદનું અનુભવ થાય છે.",
  "tamil": "உலகின் மாறுபாடு, துன்பம் ஆகியவற்றில் உயர்ந்த பட்டம் அல்லது புனிதம் தேவை இல்லை; மனதைத் தெய்வத்திற்கு அர்ப்பணிக்க வேண்டும்.  \nஅதைச் செய்வதால் மனம் அமைதியையும் ஆன்மீக சுதந்திரத்தையும் பெறும்.  \nஇது வாழ்க்கையின் அலைகளை அசையாமல், உண்மையான மகிழ்ச்சியை அனுபவிக்க உதவும்.",
  "telugu": "బ్రాహ్మణులు, రాజులు, భక్తులు కూడా ప్రపంచపు అనిత్య బాధలలో చిక్కుకుంటారు; దానికి పరిష్కారం, పరమాత్మను సత్యంగా భజించడం.  \nఇది మనకు శాశ్వత శాంతి, సుఖాన్ని అందిస్తుంది.  \nఅంతేకాక, జీవనంలో నిజమైన స్వేచ్ఛ, ఆత్మ‑సంతృప్తి లభిస్తుంది.",
  "kannada": "ಈ ಲೋಕದ ಅಸ್ಥಿರತೆ ಮತ್ತು ದುಃಖದಿಂದ ಬೇಸರವಾಗಿರುವಾಗ, ಪವಿತ್ರ ಜನರ ಜೊತೆ ತೊಡಗಿಕೊಳ್ಳುವ ಬದಲು, ನೇರವಾಗಿ ಭಗವಂತನನ್ನು ಭಜಿಸೋಣ.  \nಇದರಿಂದ ಮನಸ್ಸು ಶಾಂತವಾಗುತ್ತದೆ, ಜೀವನದ ಅಸ್ಥಿರತೆಯ ಭಯ ಕಡಿಮೆಯಾಗುತ್ತದೆ.  \nಅಂತಿಮವಾಗಿ ಆತ್ಮದ ಶಾಶ್ವತ ಸಂತೋಷ ಮತ್ತು ಮುಕ್ತಿಯನ್ನು ಪಡೆಯುತ್ತೇವೆ."
}