{
  "chapter": "2",
  "verse": "2.39",
  "sanskrit_verse": "एषा तेऽभिहिता साङ्ख्ये बुद्धिर्योगे त्विमां शृणु। बुद्ध्या युक्तो यया पार्थ कर्मबन्धं प्रहास्यसि॥",
  "sanskrit": "कर्मबन्धनस्य चिन्ता मनसि, बुद्ध्या योगे संयुज्य निःस्वार्थं कर्म कर्तुं।  \nतत् कृत्वा मोक्षस्य प्रकाशः, शान्ति च हृदयस्य प्राप्तिः।  \nजीवनस्य सुखं स्थैर्यं च, आत्मसाक्षात्कारस्य मार्गः।",
  "punjabi": "ਜਦੋਂ ਅਸੀਂ ਕਰਮਾਂ ਦੀ ਬੋਝ ਅਤੇ ਉਦੇਸ਼ ਦੀ ਉਲਝਣ ਵਿੱਚ ਫਸ ਜਾਂਦੇ ਹਾਂ, ਤਦ ਸਾਂਖ੍ਯਾ ਦੀ ਬੁੱਧੀ ਨੂੰ ਯੋਗ ਵਿੱਚ ਲਾਗੂ ਕਰਨਾ ਹੱਲ ਹੈ।  \nਇਸ ਬੁੱਧੀ ਨਾਲ ਅਸੀਂ ਕਰਮ‑ਬੰਧਨ ਤੋਂ ਮੁਕਤ ਹੋ ਕੇ ਮਨ ਦੀ ਸ਼ਾਂਤੀ ਪ੍ਰਾਪਤ ਕਰਦੇ ਹਾਂ।  \nਸਚੇਤਨਾ ਅਤੇ ਸਵੈ‑ਨਿਯੰਤਰਣ ਨਾਲ ਜੀਵਨ ਵਿੱਚ ਸਪਸ਼ਟਤਾ ਅਤੇ ਆਤਮ‑ਵਿਸ਼ਵਾਸ ਵਧਦਾ ਹੈ।",
  "hindi": "जब मन कार्य‑कर्म में फँस कर बेचैनी महसूस करता है, तो साङ्ख्य‑बुद्धि को योग के साथ मिलाकर विवेकपूर्ण कार्य करना चाहिए।  \nऐसे करने से कर्म‑बंधन टूटता है और मन में शांति स्थापित होती है।  \nपरिणामस्वरूप आत्म‑साक्षात्कार की दिशा में स्थिर प्रगति मिलती है।",
  "english": "When anxiety about duty and fear of being trapped by actions arise, cultivate clear discrimination (buddhi) through the practice of yoga.  \nThat insight breaks the mental chains that bind you to repetitive results.  \nYou then experience lasting inner peace and the confidence to act without attachment.",
  "gujarati": "ક્રિયાઓની બંધનથી તણાવમાં રહેલા મનને, સાંખ્યનું જ્ઞાન અને યોગનું",
  "tamil": "வாழ்க்கையின் கடமைகளில் சிக்கி, செயலின் பிணைப்பு பயப்படுகிறாய்; அறிவும் யோகமும் ஒன்றாகக் கொண்டு, மனதின் தெளிவை பெற வேண்டும்.  \nஇவ்வாறு அறிவுடன் செயல்பட்டால், குணமற்ற செயல்பாட்டின் சங்கிலி உடைந்து, உள்ளார்ந்த சுதந்திரம் கிடைக்கும்.  \nஇதனால் மனம் அமைதியுடன், வாழ்க்கையின் ஒவ்வொரு தருணமும் தெளிவாக அனுபவித்து, ஆன்மீக வளர்ச்சியை அடையலாம்.",
  "telugu": "కార్య‑బంధం, ఆందోళనలతో చిక్కుకుపోయినప్పుడు, జ్ఞాన‑యోగాన్ని అనుసరించి, బుద్ధితో కలసి చర్యల బంధాన్ని విడిచిపెట్టాలి.  \nఇది మనకు అంతర్గత శాంతి, స్వేచ్ఛను అందిస్తుంది.  \nఅదనంగా, నిజమైన జ్ఞానం ద్వారా జీవన‑లక్ష్యాన్ని స్పష్టంగా చూసి, సుఖ‑సమృద్ధి పొందవచ్చు.",
  "kannada": "ಕರ್ಮದ ಭಾರ ಮತ್ತು ಮನಸ್ಸಿನ ಅಶಾಂತಿಗೆ, ಬುದ್ಧಿ‑ಯೋಗದ ಜ್ಞಾನದಿಂದ ಕಾರ್ಯ ನಿರ್ವಹಿಸುವುದು ಪರಿಹಾರ.  \nಇದರಿಂದ ಕರ್ಮಬಂಧನ ಮುರಿದು, ಮನಸ್ಸು ಶಾಂತವಾಗುತ್ತದೆ.  \nಶ"
}