{
  "chapter": "13",
  "verse": "13.26",
  "sanskrit_verse": "अन्ये त्वेवमजानन्तः श्रुत्वान्येभ्य उपासते। तेऽपि चातितरन्त्येव मृत्युं श्रुतिपरायणाः॥",
  "sanskrit": "श्रवणस्यैव आश्रयेण बन्धनं मन्यन्ते जनाः, परन्तु आत्मज्ञानं अन्वेष्टुं प्रयत्नं कुर्वन्तु।  \nएवं कृत्वा मोक्षस्य प्रकाशः स्फुटितो भवति।  \nशान्तिपूर्णं जीवनं लभ्यते, मृत्युः भयविहीनः भवति।",
  "punjabi": "ਸੁਣੀ ਹੋਈ ਧਾਰਮਿਕ ਰੀਤਾਂ 'ਤੇ ਟਿਕ ਕੇ ਰਹਿਣਾ ਮਨੁੱਖੀ ਗਲਤੀ ਹੈ; ਅਸਲ ਸਚਾਈ ਦੀ ਖੋਜ ਕਰਕੇ ਆਪਣੀ ਆਤਮਾ ਨੂੰ ਜਾਣੋ।  \nਇਸ ਨਾਲ ਮੌਤ ਦੇ ਚੱਕਰ ਤੋਂ ਉੱਪਰ ਉਠ ਕੇ ਸ਼ਾਂਤੀ ਅਤੇ ਮੁਕਤੀ ਮਿਲਦੀ ਹੈ।  \nਸੱਚੀ ਸਮਝ ਨਾਲ ਜੀਵਨ ਦੀਆਂ ਹਰ ਚੁਣੌਤੀਆਂ ਨੂੰ ਸਹਿਜੀ ਨਾਲ ਨਿਭਾਇਆ ਜਾ ਸਕਦਾ ਹੈ।",
  "hindi": "कई लोग केवल शास्त्र सुनकर ही पूजा‑पाठ करते हैं और असली आत्म‑ज्ञान नहीं खोजते; समाधान है श्रोत‑भ्रम को त्याग कर प्रत्यक्ष ज्ञान की खोज करना।  \nऐसा करने से मृत्यु के भय से मुक्ति मिलती है और मन में शांति व स्थिरता स्थापित होती है।  \nअंत में आत्मा की शाश्वत प्रकृति का अनुभव होता है, जिससे जीवन में सच्चा आनंद और मुक्तिदायक दृष्टि आती है।",
  "english": "When we worship without truly knowing the Supreme, we remain stuck in ignorance and the endless cycle of birth and death.  \nRealizing the one ultimate source and directing our devotion to it breaks that cycle.  \nThat understanding brings lasting peace, purpose, and liberation beyond all future deaths.",
  "gujarati": "ઘણા લોકો માત્ર શબ્દો સાંભળીને અન્ય દેવતાઓની ઉપાસના કરે છે, જે અજ્ઞાનનું કારણ બને છે; સાચો ઉપાય છે આત્મજ્ઞાનની શોધ અને શ્રુતિ પર અતિ નિર્ભરતા છોડવી.  \nજ્યારે આપણે જ્ઞાનને પ્રાથમિકતા આપીએ છીએ, ત્યારે મૃત્યુની ભયથી મુક્તિ મળે છે અને જીવનમાં શાંતિ પ્રગટે છે.  \nઆ રીતે મનનું નિર્વાણ થાય છે, અને સત્યની અનુભૂતિથી સર્વવ્યાપી પ્રેમ અને સુખ પ્રાપ્ત થાય છે.",
  "tamil": "உண்மையை அறியாமல் வேதப் பாகங்களை மட்டும் படித்து வழிபடும் பலர், இறப்பைத் தவிர்க்க ஆழமான அறிவைத் தேட வேண்டும்.  \nஅறிவின் வெளிச்சம் மனதை அமைதியுடன் நிரப்பி, வாழ்க்கைக்கு தெளிவை தரும்.  \nசுயவிடுதலைப் பெறும் போது பிறப்பும் மரணமும் சுழற்சியிலிருந்து விடுபட்டு, நித்திய சாந்தியை அனுபவிப்போம்.",
  "telugu": "శాస్త్రాల సారాన్ని గ్రహించకపోతే, ఇతర దేవతలను పూజించడం కూడా మోసమే; జ్ఞానం పొందడం ద్వారా నిజ మార్గం దొరుకుతుంది.  \nజ్ఞానం పొందినవారు మోక్షాన్ని చేరి, జీవనంలో శాంతి, సంతోషాన్ని అనుభవిస్తారు.  \nబాహ్య పూజలపై ఆధారపడకుండా, అంతర్గత జ్ఞానాన్ని పెంపొందించుకోవడం ద్వారా సత్యాన్ని స్పష్టంగా తెలుసుకోవచ్చు.",
  "kannada": "ಜ್ಞಾನವಿಲ್ಲದೆ ಕೇವಲ ಶ್ರವಣ ಮತ್ತು ಪೂಜೆಗೆ ಅಂಟಿಕೊಂಡಿರುವವರು, ಆತ್ಮಸಾಕ್ಷಾತ್ಕಾರವನ್ನು ಹುಡುಕುವ ಮೂಲಕ ಈ ಬಂಧನವನ್ನು ಮುರಿಯಬಹುದು.  \nಇದರಿಂದ ಜೀವನದಲ್ಲಿ ನಿಜವಾದ ಶಾಂತಿ ಮತ್ತು ಸ್ವಯಂ ಅರಿವು ಬೆಳೆಯುತ್ತದೆ.  \nಅಂತಿಮವಾಗಿ ಮರಣದ ಭಯ ಮತ್ತು ಭ್ರಾಂತಿಗಳಿಂದ ಮುಕ್ತವಾಗಿ, ಪರಮಾತ್ಮದೊಂದಿಗೆ ಏಕತೆಯನ್ನು ಅನುಭವಿಸಬಹುದು."
}