{
  "chapter": "16",
  "verse": "16.9",
  "sanskrit_verse": "एतां दृष्टिमवष्टभ्य नष्टात्मानोऽल्पबुद्धय: | प्रभवन्त्युग्रकर्माण: क्षयाय जगतोऽहिता: ||",
  "sanskrit": "आत्मदृष्टेः अभावेन मनुष्यः अल्पबुद्धिं प्राप्य कुप्रवृत्तिं करोति; अतः सत्यम् दृष्ट्वा शान्तिं ध्यायेत्।  \nएवं शान्तिप्राप्तिः हृदयस्य शुद्धिं ददाति।  \nजगतः क्षयः निवार्य विश्वे सौहार्दं सिध्यति।",
  "punjabi": "ਜਦੋਂ ਅਸੀਂ ਆਤਮਿਕ ਦ੍ਰਿਸ਼ਟੀ ਗੁਆ ਲੈਂਦੇ ਹਾਂ, ਛੋਟੀ ਸੋਚ ਤੇ ਅਗਿਆਨਤਾ ਨਾਲ ਨਕਾਰਾਤਮਕ ਕਰਮ ਕਰਦੇ ਹਾਂ; ਇਸ ਲਈ ਸਚੇਤਨਤਾ ਅਤੇ ਗਿਆਨ ਦੀ ਅਭਿਆਸ ਕਰੀਏ।  \nਇਸ ਨਾਲ ਮਨ ਦੀ ਸ਼ਾਂਤੀ ਮਿਲਦੀ ਹੈ ਅਤੇ ਆਪ ਨੂੰ ਨੁਕਸਾਨ ਤੋਂ ਬਚਾਇਆ ਜਾਂਦਾ ਹੈ।  \nਸਮਾਜ ਵਿੱਚ ਸ਼ਾਂਤੀ ਅਤੇ ਸਚਾਈ ਫੈਲਦੀ ਹੈ, ਜੋ ਸੰਸਾਰ ਦੀ ਖ਼ਰਾਬੀ ਨੂੰ ਰੋਕਦੀ ਹੈ।",
  "hindi": "जब हम आत्म‑ज्ञान की दृष्टि खोकर छोटा‑बुद्धि बन जाते हैं, तो शांति से आत्म‑साक्षात्कार की खोज करनी चाहिए।  \nऐसा करने से मन की अंधकार दूर हो कर स्पष्टता आती है, जिससे विनाशकारी कार्यों से बचाव होता है।  \nपरिणामस्वरूप न केवल हमारा व्यक्तिगत जीवन सुदृढ़ होता है, बल्कि समाज और पृथ्वी की समरसता भी बनी रहती है।",
  "english": "When we forget our true nature and let a limited mind dominate, we act harshly and damage both ourselves and the world...so we must regain clear self‑vision through sincere self‑inquiry.  \nThis awakens wisdom, steadies the mind, and ends the cycle of destructive actions.  \nConsequently, inner peace blossoms and radiates outward, fostering personal well‑being and a healthier world.",
  "gujarati": "જ્યારે આત્મજ્ઞાનની દૃષ્ટિ ખોવાઈ જાય છે, ત્યારે અંધકારમાં ફસાઈને હિંસક અને વિનાશકારી કાર્યોમાં પડીએ છીએ; નિયમિત ધ્યાન અને શાસ્ત્રોનું અધ્યયન કરીને સાચી આત્મદૃષ્ટિ પુનઃપ્રાપ્ત કરવી જોઈએ.  \nઆથી મનમાં શાંતિ અને સ્પષ્ટતા આવે છે, જે વ્યક્તિને સત્ય અને કરુણાની માર્ગે આગળ ધપાવે છે.  \nસમાજમાં શાંતિ અને સુખનું પ્રસાર થાય છે, અને જગતનું નાશ અટકી જાય છે.",
  "tamil": "தெய்வீக பார்வை இழந்து, சிறிய அறிவால் கடுமையான செயல்களில் விழும் மனநிலையை மாற்ற, சுயம் மற்றும் பிரபஞ்சம் பற்றிய உண்மையான அறிவை மீண்டும் பெற வேண்டும்.  \nஇதைப் பின்பற்றினால், தீய செயல்கள் குறைந்து, உள்ளார்ந்த அமைதி மற்றும் தெளிவை அனுபவிப்போம்.  \nஅதனால், தனிநபரின் வளர்ச்சியும், உலகின் சமநிலையும் பாதுகாக்கப்படும்.",
  "telugu": "స్పష్టమైన సత్య దృష్టి లేకపోవడం మన ఆత్మను నాశనం చేస్తుంది; అంతకంటే చిన్న బుద్ధి కలవారు హింసాత్మక చర్యలలో నిమగ్నమై, ప్రపంచాన్ని క్షీణింపజేస్తారు...అందుకే నిజమైన జ్ఞానాన్ని పొందడం, సత్యాన్ని చూసే దృష్టిని అభివృద్ధి చేయాలి.  \nసత్య దృష్టితో జీవిస్తే మన అంతఃస్థితి శాంతి, స్థిరత్వం పొందుతుంది.  \nఅలా చేయడం ద్వారా హింస తగ్గి, సమాజం, ప్రపంచం సౌభాగ్యంతో, సుస్థిరంగా వికసిస్తుంది.",
  "kannada": "ಸ್ವಯಂ ಗುರುತಿನ ದೃಷ್ಟಿ ಕಳೆದು ಅಲ್ಪಬುದ್ಧಿ ಜನರು ಕಠಿಣ ಕಾರ್ಯಗಳಲ್ಲಿ ಮುಳುಗುವ ಸಮಸ್ಯೆ, ಇದನ್ನು ತೊರೆದು ಆತ್ಮಜ್ಞಾನವನ್ನು ಅರಿತು ಶಾಂತವಾಗಿ ಕಾರ್ಯನಿರ್ವಹಿಸಬೇಕು.  \nಇದರಿಂದ ಒಳಗಿನ ಶಾಂತಿ ಮತ್ತು ಸಮತೋಲನ ಬಲವಾಗುತ್ತದೆ, ಅಹಂಕಾರ ಹಾಗೂ ಕ್ರೋಧ ಕಡಿಮೆಯಾಗುತ್ತದೆ.  \nಸಮಾಜದಲ್ಲಿ ಶಾಂತಿ ಮತ್ತು ಸಕಾರಾತ್ಮಕ ಪ್ರಭಾವ ವೃದ್ಧಿ ಹೊಂದುತ್ತದೆ, ಜಗತ್ತಿನ ಕ್ಷಯವನ್ನು ತಡೆಯುವಲ್ಲಿ ಸಹಾಯವಾಗುತ್ತದೆ."
}