{
  "chapter": "16",
  "verse": "16.21",
  "sanskrit_verse": "त्रिविधं नरकस्येदं द्वारं नाशनमात्मन: | काम: क्रोधस्तथा लोभस्तस्मादेतत्त्रयं त्यजेत् ||",
  "sanskrit": "कामक्रोधलोभ इत्येते त्रयः आत्मनः बन्धकाः, तेषां त्यागः शान्तिम् आवहति।  \nबन्धनविमुक्ते हृदयम् शुद्धम् भवति, सुखस्य स्थायित्वम् लभते।  \nनिःस्वार्थभावेन जीवनम् प्रकाशते, मोक्षमार्गेण आत्मा मुक्तिं प्राप्नोति।",
  "punjabi": "ਲਾਲਚ, ਕ੍ਰੋਧ ਅਤੇ ਤਮਨਾ ਮਨ ਦੇ ਤਿੰਨ ਅੱਗ ਦੇ ਦਰਵਾਜ਼ੇ ਹਨ; ਇਨ੍ਹਾਂ ਨੂੰ ਛੱਡਣਾ ਹੀ ਅਸਲੀ ਆਜ਼ਾਦੀ ਦੀ ਕੁੰਜੀ ਹੈ।  \nਜਦੋਂ ਅਸੀਂ ਇਨ੍ਹਾਂ ਤਿੰਨ ਨੂੰ ਤਿਆਗਦੇ ਹਾਂ, ਮਨ ਸ਼ਾਂਤ ਰਹਿੰਦਾ ਹੈ ਅਤੇ ਜੀਵਨ ਵਿੱਚ ਸੱਚੀ ਖੁਸ਼ੀ ਆਉਂਦੀ ਹੈ।  \nਇਸ ਤਰ੍ਹਾਂ ਸਾਡੀ ਆਤਮਿਕ ਪ੍ਰਗਤੀ ਤੇ ਸੰਸਾਰਿਕ ਬੰਧਨਾਂ ਤੋਂ ਮੁਕਤੀ ਮਿਲਦੀ ਹੈ।",
  "hindi": "इच्छा, क्रोध और लोभ... ये तीन भावनाएँ हमारे मन को अंधकार में ले जाती हैं; इन्हें त्यागना ही शांति का पहला कदम है।  \nइन बंधनों को छोड़ने से मन में शुद्धता आती है और आत्म‑संतोष का अनुभव होता है।  \nपरिणामस्वरूप जीवन में स्थिरता, सच्ची खुशी और मोक्ष की ओर अग्रसरता मिलती है।",
  "english": "When craving, rage, and greed take over, they become the gateway to suffering; dropping these three poisons restores inner balance.  \nFreeing yourself from them steadies the mind, ending self‑destruction and inner turmoil.  \nWith that calm, you experience lasting peace, clear insight, and true spiritual freedom.",
  "gujarati": "ઈચ્છા, ક્રોધ અને લોભ જેવા ત્રિગુણ કષ્ટો આપણા જીવનમાં અંધકારનું દ્વાર ખોલે છે; તેને છોડીને મનને શુદ્ધ કરવું એ મુખ્ય ઉપાય છે.  \nઆ ત્રણે ત્યાગવાથી મનની શાંતિ અને આંતરિક સ્વતંત્રતા મળે છે.  \nપરિણામે સત્ય અને આનંદની પ્રાપ્તિ થાય છે, જીવનમાં સુખ અને સમૃદ્ધિનો માર્ગ ખુલ્લો થાય છે.",
  "tamil": "ஆசை, கோபம், லோபம் ஆகிய மூன்று தீய உணர்வுகள் வாழ்க்கையின் நரக கதவுகள்; அவற்றை விட்டு விலகுவது ஆன்மாவின் விடுதலைக்கு முதல் படி.  \nஇவற்றை விட்டால் மனம் சாந்தியையும் தெளிவையும் பெறும், சுயஅறிவை வளர்க்கும்.  \nஇதனால் பாவம் குறைந்து, சுயநிறைவு மற்றும் ஆன்மீக முன்னேற்றம் எளிதாகும்.",
  "telugu": "కోరిక, కోపం, లోభం అనే మూడు విషాదాలు మన జీవితాన్ని నరకపు ద్వారంగా మార్చుతాయి; వాటిని వదిలి ఆత్మ శుద్ధి మార్గాన్ని ఎంచుకోవాలి.  \nఇది మన మనసును ప్రశాంతంగా, సంతోషంగా, స్వేచ్ఛగా మార్చి, అంతర్గత సమతుల్యాన్ని అందిస్తుంది.  \nఅంతిమంగా, ఆధ్యాత్మిక వికాసం, సత్య జ్ఞానం, పరమ శాంతి అనుభవించగలము.",
  "kannada": "ಕಾಮ, ಕ್ರೋಧ, ಲೋಭ ಎಂಬ ಮೂರು ಅತೃಪ್ತಿಗಳು ನಮ್ಮ ಮನಸ್ಸನ್ನು ನೋವಿನ ಬಾಗಿಲುಗಳಂತೆ ತೋರುತ್ತವೆ; ಅವುಗಳನ್ನು ತೊರೆದು ಶಾಂತಿಯನ್ನು ಆಯ್ಕೆ ಮಾಡೋಣ.  \nಇದರಿಂದ ಮನಸ್ಸು ಶುದ್ಧವಾಗುತ್ತದೆ, ಆತ್ಮಸಂತೃಪ್ತಿ ಮತ್ತು ಒಳಗಿನ ಶಾಂತಿಯನ್ನು ಪಡೆಯುತ್ತೇವೆ.  \nಜೀವನದಲ್ಲಿ ಸ್ಪಷ್ಟತೆ, ಸಮಾಧಾನ ಮತ್ತು ಪ್ರಗತಿಯ ಹಾದಿ ಸುಲಭವಾಗಿ ತೆರೆಯುತ್ತದೆ."
}