{
  "chapter": "17",
  "verse": "17.21",
  "sanskrit_verse": "यत्तु प्रत्युपकारार्थं फलमुद्दिश्य वा पुन: | दीयते च परिक्लिष्टं तद्दानं राजसं स्मृतम् ||",
  "sanskrit": "परिचर्यायां यदि प्रत्युपकारस्य आशया कर्ता व्याकुलः, तर्हि फलम् उद्दिश्य दानं राजसम् इव दातव्यम्।  \nएवं दानं कृत्वा आत्मसन्तोषं च सामाजिकमान्यतां लभते।  \nपरिणामे सुखसमृद्धिः, धैर्यं च वर्धते।",
  "punjabi": "ਜਦੋਂ ਅਸੀਂ ਕਿਸੇ ਨੂੰ ਲਾਭ ਦੀ ਉਮੀਦ ਨਾਲ ਜਾਂ ਔਖੀ-ਮੁਸ਼ਕਲ ਤੋਹਫ਼ਾ ਦੇ ਕੇ ਦਾਨ ਕਰਦੇ ਹਾਂ, ਇਹ ਰਾਜਸਿਕ ਦਾਨ ਬਣ ਜਾਂਦਾ ਹੈ; ਇਸ ਲਈ ਬਿਨਾ ਕਿਸੇ ਫ਼ਾਇਦੇ ਦੀ ਉਮੀਦ ਦੇ ਸੱਚੀ ਨਿਸ਼ਕਪਟਤਾ ਨਾਲ ਦਾਨ ਕਰੀਏ।  \nਇਸ ਤਰ੍ਹਾਂ ਦੀ ਨਿਸ਼ਕਪਟ ਦਾਨੀਅਤ ਮਨ ਨੂੰ ਸ਼ਾਂਤੀ ਅਤੇ ਆਤਮਿਕ ਸ਼ੁੱਧੀ ਦਿੰਦੀ ਹੈ।  \nਇਹ ਸੱਚੀ ਦਾਨੀਅਤ ਸਾਡੇ ਰਿਸ਼ਤਿਆਂ ਨੂੰ ਮਜ਼ਬੂਤ ਕਰਦੀ ਹੈ ਅਤੇ ਜੀਵਨ ਵਿੱਚ ਖੁਸ਼ੀ ਤੇ ਸੰਤੁਸ਼ਟੀ ਲਿਆਉਂਦੀ ਹੈ।",
  "hindi": "जब हम उपकार की आशा या जटिल शर्तों के साथ दान करते हैं, तो वह रजस‑स्वभाव का कार्य बन जाता है; इसे छोड़कर निःस्वार्थ और सरलता से देना चाहिए।  \nऐसा करने से मन में लगाव घटता है, शांति और संतोष का अनुभव होता है।  \nपरिणामस्वरूप जीवन में सच्ची खुशी और स्थायी संतुलन स्थापित होता है।",
  "english": "When we give expecting something in return—especially with effort or strain—we’re caught in selfish desire, so the remedy is to offer freely, without any expectation of reward.  \nDoing this dissolves the restless, passion‑driven mindset and brings inner calm.  \nIt also cultivates true generosity, fostering lasting harmony and spiritual growth.",
  "gujarati": "જ્યારે આપણે ફળની અપેક્ષા રાખીને ભેટ આપીએ છીએ, ત્યારે તે રાજસિક ગણાય છે; તેથી નિષ્કપટ અને સરળ રીતે દાન કરવું જોઈએ।  \nએવું નિષ્કપટ દાન આપવાથી મનમાં શાંતિ અને શુદ્ધતા આવે છે।  \nઆથી આત્મિક પ્રગતિ અને સત્ય સુખની અનુભૂતિ મળે છે।",
  "tamil": "நாம் ஏதோ நலனுக்காகப் பரிசு கொடுக்க விரும்பும் போது, எதிர்பார்ப்பு இல்லாமல் தன்னலமற்ற முறையில் கொடுப்பதே தீர்வு.  \nஇது மனதை சுத்தமாக்கி, ஆன்மீக அமைதியையும் உள்ளார்ந்த மகிழ்ச்சியையும் தரும்.  \nஅதனால் வாழ்க்கைச் சுமைகள் குறைந்து, உண்மையான அன்பும் பரஸ்பர ஒற்றுமையும் வளர்கிறது.",
  "telugu": "ఇతరులకు బహుమతి ఇవ్వడానికి ప్రతిఫలం ఆశించడం వల్ల సంకోచించే మనసుకు, అది కూడా రాజు చేసిన దానిలా గౌరవించబడుతుంది.  \nఇలా ఇచ్చి, మనకు సమాజంలో గౌరవం, విశ్వాసం పెరుగుతాయి.  \nఅదే సమయంలో, హృదయంలో సంతృప్తి, ఆత్మీయ శాంతి కూడా కలుగుతుంది.",
  "kannada": "ಜನರು ಪ್ರತಿಫಲ ನಿರೀಕ್ಷೆಯಿಂದ ಅಥವಾ ಕಷ್ಟಕರವಾಗಿ ದಾನ ಮಾಡುತ್ತಾರೆ; ದಾನವನ್ನು ನಿರೀಕ್ಷೆ ಇಲ್ಲದೆ, ಸರಳವಾಗಿ ಮತ್ತು ನಿಸ್ವಾರ್ಥವಾಗಿ ನೀಡುವುದು ಪರಿಹಾರ.  \nಇದರಿಂದ ಹೃದಯ ಶುದ್ಧವಾಗುತ್ತದೆ, ಆತ್ಮದಲ್ಲಿ ಶಾಂತಿ ಮತ್ತು ಸಂತೃಪ್ತಿ ಉಂಟಾಗುತ್ತದೆ.  \nಕರ್ಮದಲ್ಲಿ ಶುಭ ಫಲಗಳು ಬಂದು, ಜೀವನದಲ್ಲಿ ಸಾಂತ್ವನ ಮತ್ತು ಪ್ರಗತಿಯನ್ನು ಅನುಭವಿಸಬಹುದು."
}